j2render.py
j2render-1.0.0.dist-info/METADATA
j2render-1.0.0.dist-info/RECORD
j2render-1.0.0.dist-info/WHEEL
j2render-1.0.0.dist-info/entry_points.txt
j2render-1.0.0.dist-info/top_level.txt
j2render-1.0.0.dist-info/zip-safe
